CHANGELOG.md
MANIFEST.in
README.md
setup.py
pyasp/__init__.py
pyasp/__main__.py
pyasp/asp.py
pyasp/constant.py
pyasp/info.py
pyasp/misc.py
pyasp/parsing.py
pyasp/term.py
pyasp.egg-info/PKG-INFO
pyasp.egg-info/SOURCES.txt
pyasp.egg-info/dependency_links.txt
pyasp.egg-info/not-zip-safe
pyasp.egg-info/top_level.txt
pyasp/bin/README.txt
pyasp/ply/__init__.py
pyasp/ply/cpp.py
pyasp/ply/ctokens.py
pyasp/ply/lex.py
pyasp/ply/yacc.py