Metadata-Version: 1.0
Name: pyasp
Version: 1.4.4
Summary: A convenience wrapper for the ASP tools gringo, gringo4 and clasp.
Home-page: http://pypi.python.org/pypi/pyasp/
Author: Sven Thiele
Author-email: sthiele78@gmail.com
License: GPLv3+
Platform: UNKNOWN
